setup.cfg
setup.py
ensembler/__init__.py
ensembler.egg-info/PKG-INFO
ensembler.egg-info/SOURCES.txt
ensembler.egg-info/dependency_links.txt
ensembler.egg-info/not-zip-safe
ensembler.egg-info/top_level.txt