Metadata-Version: 1.0
Name: ensembler
Version: 0.2
Summary: A python package for ensemling models via Stacking/Bleanding, bagging etc
Home-page: https://github.com/pankajr141/ensembler
Author: Pankaj Rawat
Author-email: pankajr141@gmail.com
License: MIT
Platform: UNKNOWN
